{
  "animateLoading": true,
  "borderRadius": "{{appsmith.theme.borderRadius.appBorderRadius}}",
  "bottomRow": 5,
  "dynamicBindingPathList": [
    {
      "key": "truncateButtonColor"
    },
    {
      "key": "fontFamily"
    },
    {
      "key": "borderRadius"
    }
  ],
  "dynamicHeight": "AUTO_HEIGHT",
  "dynamicTriggerPathList": [],
  "fontFamily": "{{appsmith.theme.fontFamily.appFont}}",
  "fontSize": "1.25rem",
  "fontStyle": "BOLD",
  "isLoading": false,
  "isVisible": true,
  "key": "im880tgvmj",
  "leftColumn": 0,
  "maxDynamicHeight": 9000,
  "minDynamicHeight": 4,
  "minWidth": 450,
  "mobileBottomRow": 5,
  "mobileLeftColumn": 1,
  "mobileRightColumn": 41,
  "mobileTopRow": 1,
  "needsErrorInfo": false,
  "overflow": "NONE",
  "parentColumnSpace": 4.306640625,
  "parentId": "tw8ygnkppt",
  "parentRowSpace": 10,
  "renderMode": "CANVAS",
  "responsiveBehavior": "fill",
  "rightColumn": 40.63492063492063,
  "shouldTruncate": false,
  "text": "Mijoz Qoshish",
  "textAlign": "LEFT",
  "textColor": "#231F20",
  "topRow": 1,
  "truncateButtonColor": "{{appsmith.theme.colors.primaryColor}}",
  "type": "TEXT_WIDGET",
  "version": 1,
  "widgetId": "nydnl8potc",
  "widgetName": "Text1"
}