{
  "animateLoading": true,
  "borderRadius": "{{appsmith.theme.borderRadius.appBorderRadius}}",
  "bottomRow": 12,
  "boxShadow": "none",
  "buttonColor": "{{appsmith.theme.colors.primaryColor}}",
  "buttonVariant": "PRIMARY",
  "disabledWhenInvalid": false,
  "dynamicBindingPathList": [
    {
      "key": "buttonColor"
    },
    {
      "key": "borderRadius"
    }
  ],
  "dynamicHeight": "FIXED",
  "dynamicPropertyPathList": [
    {
      "key": "onClick"
    }
  ],
  "dynamicTriggerPathList": [
    {
      "key": "onClick"
    }
  ],
  "iconAlign": "left",
  "iconName": "minus",
  "isDefaultClickDisabled": true,
  "isDisabled": false,
  "isLoading": false,
  "isVisible": true,
  "key": "er9v4cxmuj",
  "leftColumn": 38,
  "minWidth": 120,
  "mobileBottomRow": 12,
  "mobileLeftColumn": 36,
  "mobileRightColumn": 52,
  "mobileTopRow": 8,
  "needsErrorInfo": false,
  "onClick": "{{const currentQuantity = dynamic.get(currentItem.id);\nif (currentQuantity > 0) {  // Optional check to prevent going negative\n  dynamic.update(currentItem.id, currentQuantity - 1);\n}\n}}",
  "parentColumnSpace": 8.8466796875,
  "parentId": "om4u7kwd35",
  "parentRowSpace": 10,
  "placement": "CENTER",
  "recaptchaType": "V3",
  "renderMode": "CANVAS",
  "resetFormOnClick": false,
  "responsiveBehavior": "hug",
  "rightColumn": 45,
  "text": "",
  "topRow": 8,
  "type": "BUTTON_WIDGET",
  "version": 1,
  "widgetId": "vawqiv4xzf",
  "widgetName": "Button1Copy"
}