{
  "gitSyncId": "63e39414576df82f0e7ee54f_6401b63c2127687553739ced",
  "id": "Orders_utils.purchaseOrderStatus",
  "pluginId": "js-plugin",
  "pluginType": "JS",
  "unpublishedAction": {
    "actionConfiguration": {
      "encodeParamsToggle": true,
      "isAsync": false,
      "jsArguments": [
        {
          "name": "status"
        }
      ],
      "paginationType": "NONE",
      "timeoutInMillisecond": 10000
    },
    "collectionId": "Orders_utils",
    "confirmBeforeExecute": false,
    "datasource": {
      "isAutoGenerated": false,
      "name": "UNUSED_DATASOURCE",
      "pluginId": "js-plugin"
    },
    "dynamicBindingPathList": [
      {
        "key": "body"
      }
    ],
    "executeOnLoad": false,
    "fullyQualifiedName": "utils.purchaseOrderStatus",
    "name": "purchaseOrderStatus",
    "pageId": "Orders",
    "userSetOnLoad": false
  }
}